conversion_utils/__init__.py
conversion_utils/conversion.py
conversion_utils-0.1.2.dist-info/METADATA
conversion_utils-0.1.2.dist-info/WHEEL
conversion_utils-0.1.2.dist-info/RECORD
