Metadata-Version: 2.1
Name: conversion_utils
Version: 0.1.2
Summary: 
Author: garfield.tong
Author-email: garfieldperfect@gmail.com
Requires-Python: >=3.10,<4.0
Classifier: Programming Language :: Python :: 3
Classifier: Programming Language :: Python :: 3.10
Classifier: Programming Language :: Python :: 3.11
Classifier: Programming Language :: Python :: 3.12
Requires-Dist: opencv-python (>=4.9.0.80,<5.0.0.0)
